nseinfopackage/__init__.py
nseinfopackage/data.py
nseinfopackage/nseinfo.py
nseinfopackage-0.1.1.dist-info/LICENSE
nseinfopackage-0.1.1.dist-info/METADATA
nseinfopackage-0.1.1.dist-info/WHEEL
nseinfopackage-0.1.1.dist-info/top_level.txt
nseinfopackage-0.1.1.dist-info/RECORD
