Metadata-Version: 2.1
Name: nseinfopackage
Version: 0.1.1
Summary: A small package that helps you in fetching getting the basic details of a specific company, or getting symbols list, of isin number list, or listed dates etc.
Author: Dr. Kumar B V
Author-email: kumar.bv@gmail.com
Classifier: Programming Language :: Python :: 3
Classifier: License :: OSI Approved :: MIT License
Classifier: Operating System :: OS Independent
Requires-Python: >=3.7
License-File: LICENSE
